crumbcutter/__about__.py
crumbcutter/__init__.py
crumbcutter/crumbcutter.py
crumbcutter-0.1.16.dist-info/METADATA
crumbcutter-0.1.16.dist-info/WHEEL
crumbcutter-0.1.16.dist-info/licenses/LICENSE.txt
crumbcutter-0.1.16.dist-info/RECORD
