Metadata-Version: 2.1
Name: crumbcutter
Version: 0.1.16
Summary: Template ONE gist file. Nothing else!
Project-URL: Documentation, https://github.com/drengskapur/crumbcutter#readme
Project-URL: Issues, https://github.com/drengskapur/crumbcutter/issues
Project-URL: Source, https://github.com/drengskapur/crumbcutter
Author-email: Drengskapur <service@drengskapur.com>
License-Expression: MIT
License-File: LICENSE.txt
Classifier: Development Status :: 4 - Beta
Classifier: Programming Language :: Python
Classifier: Programming Language :: Python :: 3.7
Classifier: Programming Language :: Python :: 3.8
Classifier: Programming Language :: Python :: 3.9
Classifier: Programming Language :: Python :: 3.10
Classifier: Programming Language :: Python :: 3.11
Requires-Python: >=3.7
Requires-Dist: click
Requires-Dist: cookiecutter
Requires-Dist: jinja2
